[
  {
    "ziyaretci_id": "Z0003",
    "ad": "Mustafa",
    "soyad": "Arslan",
    "telefon": "05131036913",
    "oncelik": 0
  },
  {
    "ziyaretci_id": "Z0004",
    "ad": "Merve",
    "soyad": "Koç",
    "telefon": "05237265590",
    "oncelik": 0
  },
  {
    "ziyaretci_id": "Z0001",
    "ad": "Mehmet",
    "soyad": "Yıldız",
    "telefon": "05445171684",
    "oncelik": 0
  },
  {
    "ziyaretci_id": "Z0000",
    "ad": "Ayşe",
    "soyad": "Arslan",
    "telefon": "05142223048",
    "oncelik": 0
  },
  {
    "ziyaretci_id": "Z0002",
    "ad": "Zeynep",
    "soyad": "Demir",
    "telefon": "05267762441",
    "oncelik": 5
  }
]